lazr.lifecycle-1.2.2-py3.13-nspkg.pth
lazr/lifecycle/__init__.py
lazr/lifecycle/event.py
lazr/lifecycle/interfaces.py
lazr/lifecycle/objectdelta.py
lazr/lifecycle/snapshot.py
lazr/lifecycle/docs/CONTRIBUTING.rst
lazr/lifecycle/docs/Makefile
lazr/lifecycle/docs/NEWS.rst
lazr/lifecycle/docs/__init__.py
lazr/lifecycle/docs/conf.py
lazr/lifecycle/docs/event.rst
lazr/lifecycle/docs/index.rst
lazr/lifecycle/docs/object-delta.rst
lazr/lifecycle/docs/snapshot.rst
lazr/lifecycle/tests/__init__.py
lazr/lifecycle/tests/test_docs.py
lazr.lifecycle-1.2.2.dist-info/COPYING.txt
lazr.lifecycle-1.2.2.dist-info/METADATA
lazr.lifecycle-1.2.2.dist-info/WHEEL
lazr.lifecycle-1.2.2.dist-info/namespace_packages.txt
lazr.lifecycle-1.2.2.dist-info/top_level.txt
lazr.lifecycle-1.2.2.dist-info/RECORD
