Metadata-Version: 2.1
Name: lazr.lifecycle
Version: 1.2.2
Summary: Richer lifecycle events API
Home-page: https://launchpad.net/lazr.lifecycle
Download-URL: https://launchpad.net/lazr.lifecycle/+download
Maintainer: LAZR Developers
Maintainer-email: lazr-developers@lists.launchpad.net
License: LGPL v3
Classifier: Development Status :: 5 - Production/Stable
Classifier: Intended Audience :: Developers
Classifier: License :: OSI Approved :: GNU Library or Lesser General Public License (LGPL)
Classifier: Operating System :: OS Independent
Classifier: Programming Language :: Python
Classifier: Programming Language :: Python :: 3
Classifier: Programming Language :: Python :: 3.8
Classifier: Programming Language :: Python :: 3.9
Classifier: Programming Language :: Python :: 3.10
Classifier: Programming Language :: Python :: 3.11
Classifier: Programming Language :: Python :: 3.12
Classifier: Programming Language :: Python :: 3.13
Requires-Python: >=3.8
License-File: COPYING.txt
Requires-Dist: setuptools
Requires-Dist: zope.interface
Requires-Dist: zope.component
Requires-Dist: zope.lifecycleevent
Requires-Dist: zope.security
Provides-Extra: docs
Requires-Dist: Sphinx; extra == "docs"
